anagrams/__init__.py
anagrams/anagrams.py
anagrams/config.py
anagrams/find_anagrams.py
anagrams/generate_anagrams.py
english-anagrams/__init__.py
english-anagrams/config.py
english-anagrams/english_anagrams.py
english-anagrams/generate_anagrams.py
english_anagrams/__init__.py
english_anagrams/anagrams.py
english_anagrams/config.py
english_anagrams/generate_anagrams.py
anagrams-0.0.5.dist-info/LICENSE
anagrams-0.0.5.dist-info/METADATA
anagrams-0.0.5.dist-info/WHEEL
anagrams-0.0.5.dist-info/top_level.txt
anagrams-0.0.5.dist-info/RECORD
