Metadata-Version: 2.1
Name: anagrams
Version: 0.0.5
Summary: A small package for finding anagrams of an english word
Home-page: https://github.com/jxmorris12/english_anagrams
Author: jxmorris12
Author-email: jxmorris12@gmail.com
License: UNKNOWN
Platform: UNKNOWN
Classifier: Programming Language :: Python :: 3
Classifier: License :: OSI Approved :: MIT License
Classifier: Operating System :: OS Independent
